serpentui/__init__.py
serpentui/app.py
serpentui/base.py
serpentui/ui.py
serpentui/utils.py
serpentui/wails.py
serpentui-2.0.0.dist-info/METADATA
serpentui-2.0.0.dist-info/WHEEL
serpentui-2.0.0.dist-info/top_level.txt
serpentui-2.0.0.dist-info/RECORD
