Metadata-Version: 2.4
Name: serpentui
Version: 2.0.0
Summary: Modern Python Desktop Apps with React, NextUI, Flask & WebView - Just Click Run!
Home-page: https://github.com/adrianez28/serpentui
Author: SerpentUI Team
Author-email: adriandevelopment.dev@gmail.com
Project-URL: Documentation, https://github.com/adrianez28/readme.md
Project-URL: Source, https://github.com/adrianez28/serpentui
Keywords: ui framework react nextui python web gui desktop flask webview
Requires-Python: >=3.8
Requires-Dist: Flask>=2.0.0
Requires-Dist: pywebview>=4.0.0
Provides-Extra: dev
Requires-Dist: pytest>=7.0; extra == "dev"
Requires-Dist: black>=22.0; extra == "dev"
Requires-Dist: mypy>=0.950; extra == "dev"
Requires-Dist: flake8>=4.0; extra == "dev"
Provides-Extra: full
Requires-Dist: Flask>=2.0.0; extra == "full"
Requires-Dist: pywebview>=4.0.0; extra == "full"
Dynamic: author
Dynamic: author-email
Dynamic: description
Dynamic: description-content-type
Dynamic: home-page
Dynamic: keywords
Dynamic: project-url
Dynamic: provides-extra
Dynamic: requires-dist
Dynamic: requires-python
Dynamic: summary
